{
    "phone": "044 9868979",
    "business_hours": [
        "ma 9-17",
        "ti-ke 9-19",
        "to-pe 9-17",
        "la 10-14"
    ],
    "catalogue": [
        {
            "header": "Leikkaukset",
            "items": [
                {
                    "name": "Leikkaus alle 30min",
                    "price": "25€"
                },
                {
                    "name": "Pitkien hiusten tasausleikkaus",
                    "price": "29€"
                },
                {
                    "name": "Leikkaus alle 45min",
                    "price": "33€"
                },
                {
                    "name": "Mallinmuutosleikkaus 60min",
                    "price": "48€"
                },
                {
                    "name": "Otsa-/niskahiusten leikkaus",
                    "price": "16€"
                },
                {
                    "name": "Koneleikkaus",
                    "price": "16€"
                },
                {
                    "name": "Leikkaus alle 7.v",
                    "price": "20€"
                },
                {
                    "name": "Leikkaus alle 12.v",
                    "price": "25€"
                },
                {
                    "name": "Mallinmuutosleikkaus alle 12.v",
                    "price": "29€"
                },
                {
                    "name": "Parran muotoilu",
                    "price": "12€"
                }
            ]
        },
        {
            "header": "Värit (yhdellä värillä värjäys)",
            "items": [
                {
                    "name": "Tyviväri max. 2cm",
                    "price": "75€"
                },
                {
                    "name": "Väri lyhyet hiukset",
                    "price": "79€"
                },
                {
                    "name": "Väri puolipitkät hiukset",
                    "price": "88€"
                },
                {
                    "name": "Väri pitkät hiukset",
                    "price": "100€"
                },
                {
                    "name": "Väri erikoispitkät hiukset",
                    "price": "120€"
                },
                {
                    "name": "Lisäpalveluna hiustenleikkaus",
                    "price": "+20€"
                }
            ]
        },
        {
            "header": "Monivärit (Usealla värillä värjäys)",
            "items": [
                {
                    "name": "Väri lyhyet hiukset",
                    "price": "85€"
                },
                {
                    "name": "Väri puolipitkät hiukset",
                    "price": "100€"
                },
                {
                    "name": "Väri pitkät hiukset",
                    "price": "125€"
                },
                {
                    "name": "Väri erikoispitkät hiukset",
                    "price": "135€"
                },
                {
                    "name": "Lisäpalveluna hiustenleikkaus",
                    "price": "+20€"
                }
            ]
        },
        {
            "header": "Vaalennukset ja raitatekniikat (hinta koostuu käytetystä ajasta ja aineista.)",
            "items": [
                {
                    "name": "Vaalennukset",
                    "price": "50€/h"
                },
                {
                    "name": "Raidoitukset",
                    "price": "50€/h"
                }
            ]
        },
        {
            "header": "Kiharakäsittelyt",
            "items": [
                {
                    "name": "Lyhyet hiukset",
                    "price": "75€"
                },
                {
                    "name": "Puolipitkät hiukset",
                    "price": "90€"
                },
                {
                    "name": "Pitkät hiukset",
                    "price": "50€/h"
                },
                {
                    "name": "Erikoispitkät hiukset",
                    "price": "50€/h"
                },
                {
                    "name": "Lisäpalveluna hiustenleikkaus",
                    "price": "+20€"
                }
            ]
        },
        {
            "header": "Olaplex-tehohoito",
            "items": [
                {
                    "name": "Olaplex-tehohoito",
                    "price": "30€"
                },
                {
                    "name": "Värjäyksen yhteydessä",
                    "price": "15€"
                },
                {
                    "name": "Vaalennuksen yhteydessä",
                    "price": "20€"
                },
                {
                    "name": "Permanentin yhteydessä",
                    "price": "25€"
                },
                {
                    "name": "Leikkauksen yhteydessä",
                    "price": "20€"
                }
            ]
        },
        {
            "header": "Ripset ja kulmat",
            "items": [
                {
                    "name": "Ripsien ja kulmien värjäys sis. muotoilu",
                    "price": "28€"
                },
                {
                    "name": "Hiusten värjäyksen yhteydessä",
                    "price": "20€"
                },
                {
                    "name": "Ripsien värjäys",
                    "price": "18€"
                },
                {
                    "name": "Kulmien värjäys sis. muotoilu",
                    "price": "18€"
                },
                {
                    "name": "Kulmien muotoilu",
                    "price": "15€"
                }
            ]
        },
        {
            "header": "Kestotaivutukset",
            "items": [
                {
                    "name": "Lash Lift Ripsien kestotaivutus ",
                    "price": "85€"
                },
                {
                    "name": "Ripsien kestotaivutus klipseillä",
                    "price": "60€"
                },
                {
                    "name": "",
                    "price": ""
                }
            ]
        },
        {
            "header": "Kampaukset",
            "items": [
                {
                    "name": "Pesu ja föönikampaus",
                    "price": "30€"
                },
                {
                    "name": "Juhlakampaus",
                    "price": "60€/h"
                },
                {
                    "name": "Hääkampaus (sis. koekampaus)",
                    "price": "120€"
                },
                {
                    "name": "Koekampaus",
                    "price": "15€ - 50€"
                }
            ]
        },
        {
            "header": "Hiustenpidennykset ",
            "items": [
                {
                    "name": "Pidennysten laitto / huolto",
                    "price": "50€/h"
                }
            ]
        },
        {
            "header": "Sunnuntaityöt hinta x 2.",
            "items": [
                {
                    "name": "",
                    "price": ""
                }
            ]
        },
        {
            "header": "Perimme peruttamaattomasta ajasta 50% palvelun hinnasta.",
            "items": [
                {
                    "name": "",
                    "price": ""
                }
            ]
        }
    ]
}
